cairocffi/VERSION
cairocffi/__init__.py
cairocffi/constants.py
cairocffi/context.py
cairocffi/ffi_build.py
cairocffi/fonts.py
cairocffi/matrix.py
cairocffi/patterns.py
cairocffi/pixbuf.py
cairocffi/surfaces.py
cairocffi/test_cairo.py
cairocffi/test_pixbuf.py
cairocffi/test_xcb.py
cairocffi/xcb.py
cairocffi/_generated/ffi.py
cairocffi/_generated/ffi_pixbuf.py
cairocffi-1.0.0.dist-info/LICENSE
cairocffi-1.0.0.dist-info/METADATA
cairocffi-1.0.0.dist-info/WHEEL
cairocffi-1.0.0.dist-info/top_level.txt
cairocffi-1.0.0.dist-info/RECORD
