Metadata-Version: 2.1
Name: cairocffi
Version: 1.0.0
Summary: cffi-based cairo bindings for Python
Home-page: https://github.com/Kozea/cairocffi
Author: Simon Sapin
Author-email: community@kozea.fr
License: BSD
Project-URL: Documentation, https://cairocffi.readthedocs.io/
Project-URL: Code, https://github.com/Kozea/cairocffi/
Project-URL: Issue tracker, https://github.com/Kozea/cairocffi/issues
Project-URL: Donation, https://www.patreon.com/kozea
Keywords: cairo,cffi,binding
Platform: Linux
Platform: macOS
Platform: Windows
Classifier: Development Status :: 5 - Production/Stable
Classifier: Intended Audience :: Developers
Classifier: License :: OSI Approved :: BSD License
Classifier: Programming Language :: Python :: 3 :: Only
Classifier: Programming Language :: Python :: 3.5
Classifier: Programming Language :: Python :: 3.6
Classifier: Programming Language :: Python :: 3.7
Classifier: Topic :: Multimedia :: Graphics
Requires-Python: >= 3.5
Requires-Dist: cffi (>=1.1.0)
Provides-Extra: doc
Requires-Dist: sphinx ; extra == 'doc'
Requires-Dist: sphinx-rtd-theme ; extra == 'doc'
Provides-Extra: test
Requires-Dist: pytest-runner ; extra == 'test'
Requires-Dist: pytest-cov ; extra == 'test'
Requires-Dist: pytest-flake8 ; extra == 'test'
Requires-Dist: pytest-isort ; extra == 'test'
Provides-Extra: xcb
Requires-Dist: xcffib (>=0.3.2) ; extra == 'xcb'
